CHANGELOG.rst
CONTRIBUTORS.rst
aioxmlrpc-0.10.0.dist-info/METADATA
aioxmlrpc-0.10.0.dist-info/WHEEL
aioxmlrpc-0.10.0.dist-info/entry_points.txt
aioxmlrpc-0.10.0.dist-info/licenses/LICENSE
aioxmlrpc/__init__.py
aioxmlrpc/client.py
aioxmlrpc/py.typed
aioxmlrpc/server.py
aioxmlrpc-0.10.0.dist-info/RECORD
