Metadata-Version: 2.1
Name: aioxmlrpc
Version: 0.10.0
Summary: XML-RPC client for asyncio
Author-Email: Guillaume Gauvrit <guillaume@gauvr.it>
License: MIT License
Classifier: Development Status :: 5 - Production/Stable
Classifier: Framework :: AsyncIO
Classifier: Intended Audience :: Developers
Classifier: Intended Audience :: Information Technology
Classifier: License :: OSI Approved :: MIT License
Classifier: Topic :: Internet :: WWW/HTTP
Classifier: Topic :: Software Development :: Libraries
Classifier: Topic :: System :: Networking
Classifier: Typing :: Typed
Classifier: Programming Language :: Python :: 3.9
Classifier: Programming Language :: Python :: 3.10
Classifier: Programming Language :: Python :: 3.11
Classifier: Programming Language :: Python :: 3.12
Classifier: Programming Language :: Python :: 3.13
Project-URL: Homepage, https://github.com/mardiros/aioxmlrpc
Project-URL: Documentation, https://github.com/mardiros/aioxmlrpc/blob/main/README.rst
Project-URL: Repository, https://github.com/mardiros/aioxmlrpc.git
Project-URL: Issues, https://github.com/mardiros/aioxmlrpc/issues
Project-URL: Changelog, https://mardiros.github.io/aioxmlrpc/user/changelog.html
Requires-Python: >=3.9
Requires-Dist: httpx<1,>=0.24
Provides-Extra: server
Requires-Dist: starlette>=0.46.2; extra == "server"
Requires-Dist: uvicorn>=0.34.1; extra == "server"
